MANIFEST.in
README.md
setup.py
hgana/__init__.py
hgana/adsorption.py
hgana/affinity.py
hgana/box.py
hgana/extract.py
hgana/mc.py
hgana/utils.py
hgana.egg-info/PKG-INFO
hgana.egg-info/SOURCES.txt
hgana.egg-info/dependency_links.txt
hgana.egg-info/requires.txt
hgana.egg-info/top_level.txt
tests/__init__.py
tests/test_simple.py