Metadata-Version: 2.1
Name: hgana
Version: 0.1.0
Summary: Analysis tool for host guest binding.
Home-page: https://github.com/Ajax23/HGAna
Author: Hamzeh Kraus
Author-email: kraus@itt.uni-stuttgart.de
License: UNKNOWN
Platform: UNKNOWN
Classifier: Programming Language :: Python :: 3
Classifier: License :: OSI Approved :: GNU General Public License v3 (GPLv3)
Classifier: Operating System :: OS Independent
Requires-Python: >=3.5
